thinknet_observer/__init__.py
thinknet_observer/calulator.py
thinknet_observer/otel.py
thinknet_observer/loggers/__init__.py
thinknet_observer/loggers/fast_logger.py
thinknet_observer/loggers/flask_logger.py
thinknet_observer/loggers/loggers.py
thinknet_observer/metrics/__init__.py
thinknet_observer/metrics/collector.py
thinknet_observer/metrics/config.py
thinknet_observer/metrics/custom_metrics_wrapper.py
thinknet_observer/metrics/fastapi_metrics_redirect.py
thinknet_observer/metrics/metrics.py
thinknet_observer/middleware/__init__.py
thinknet_observer/middleware/fast_middleware.py
thinknet_observer/middleware/flask_middleware.py
thinknet_observer/utils/__init__.py
thinknet_observer/utils/bcolor.py
thinknet_observer/utils/gunicorn_multiprocess.py
thinknet_observer/utils/health.py
thinknet_observer/utils/http.py
thinknet_observer/utils/singleton.py
tn_observer-0.5.6.dist-info/LICENSE.txt
tn_observer-0.5.6.dist-info/METADATA
tn_observer-0.5.6.dist-info/WHEEL
tn_observer-0.5.6.dist-info/top_level.txt
tn_observer-0.5.6.dist-info/RECORD
