Metadata-Version: 2.1
Name: tn-observer
Version: 0.5.6
Summary: library for data observerability in our company THiNKNET via opentelemetry
Author-email: capukampan <capukampan22@gmail.com>, THiNKNET <sorapol@thinknet.co.th>
Keywords: thinknet,observerability
Requires-Python: >=3.7
License-File: LICENSE.txt
Requires-Dist: prometheus-client
Requires-Dist: Flask
Requires-Dist: fastapi
Requires-Dist: kafka-python >=2.0.0
Requires-Dist: opentelemetry-api
Requires-Dist: opentelemetry-sdk
Requires-Dist: opentelemetry-exporter-otlp
Requires-Dist: opentelemetry-exporter-otlp-proto-grpc
Requires-Dist: opentelemetry-instrumentation
Requires-Dist: opentelemetry-instrumentation-requests
Requires-Dist: opentelemetry-instrumentation-flask
Requires-Dist: opentelemetry-instrumentation-fastapi
Requires-Dist: opentelemetry-instrumentation-pymongo
Requires-Dist: opentelemetry-instrumentation-kafka-python
Requires-Dist: opentelemetry-instrumentation-pika
